awstriggers/__init__.py
awstriggers/cloudwatchtriggers.py
awstriggers/exceptions.py
awstriggers/s3triggers.py
awstriggers/sqstriggers.py
awstriggers-0.0.1.dist-info/DESCRIPTION.rst
awstriggers-0.0.1.dist-info/METADATA
awstriggers-0.0.1.dist-info/RECORD
awstriggers-0.0.1.dist-info/WHEEL
awstriggers-0.0.1.dist-info/metadata.json
awstriggers-0.0.1.dist-info/top_level.txt
