Metadata-Version: 2.0
Name: awstriggers
Version: 0.0.1
Summary: Simple classes for AWS trigger records and events.
Home-page: https://github.com/JevyanJ/awstriggers
Author: JevyanJ
Author-email: jjrg184@gmail.com
License: UNKNOWN
Platform: UNKNOWN
Classifier: Programming Language :: Python :: 3
Classifier: License :: OSI Approved :: MIT License
Classifier: Operating System :: OS Independent
Requires-Python: >=3.6
